CHANGES.txt
DEPENDENCES.txt
README.txt
setup.py
src/pd/__init__.py
src/pd.requires.egg-info/PKG-INFO
src/pd.requires.egg-info/SOURCES.txt
src/pd.requires.egg-info/dependency_links.txt
src/pd.requires.egg-info/entry_points.txt
src/pd.requires.egg-info/namespace_packages.txt
src/pd.requires.egg-info/not-zip-safe
src/pd.requires.egg-info/requires.txt
src/pd.requires.egg-info/top_level.txt
src/pd/requires/__init__.py
src/pd/requires/find_provides.py
src/pd/requires/find_requires.py
src/pd/requires/imalyzer.py
src/pd/requires/pd.requires.txt
src/pd/requires/provides.py
src/pd/requires/requires.py
