Metadata-Version: 1.0
Name: pd.requires
Version: 0.0.3
Summary: Module and tools used to do dependenes analys in python modules
Home-page: http://www.dreambot.ru/product/DreamBotOtherReleases/pd.requires
Author: Andrey Orlov
Author-email: cray@neural.ru
License: GPL v2.1
Platform: UNKNOWN
Classifier: Intended Audience :: Developers
Classifier: License :: OSI Approved :: GNU General Public License (GPL)
Classifier: Programming Language :: Python
Classifier: Operating System :: OS Independent
